odoo/addons/stock_available_base_exclude_location/README.rst
odoo/addons/stock_available_base_exclude_location/__init__.py
odoo/addons/stock_available_base_exclude_location/__manifest__.py
odoo/addons/stock_available_base_exclude_location/i18n/stock_available_base_exclude_location.pot
odoo/addons/stock_available_base_exclude_location/models/__init__.py
odoo/addons/stock_available_base_exclude_location/models/product_product.py
odoo/addons/stock_available_base_exclude_location/models/stock_exclude_location_mixin.py
odoo/addons/stock_available_base_exclude_location/readme/CONTRIBUTORS.rst
odoo/addons/stock_available_base_exclude_location/readme/DESCRIPTION.rst
odoo/addons/stock_available_base_exclude_location/readme/USAGE.rst
odoo/addons/stock_available_base_exclude_location/static/description/icon.png
odoo/addons/stock_available_base_exclude_location/static/description/index.html
odoo/addons/stock_available_base_exclude_location/tests/__init__.py
odoo/addons/stock_available_base_exclude_location/tests/common.py
odoo/addons/stock_available_base_exclude_location/tests/test_stock_exclude_location.py
odoo14_addon_stock_available_base_exclude_location-14.0.1.0.2.dist-info/METADATA
odoo14_addon_stock_available_base_exclude_location-14.0.1.0.2.dist-info/WHEEL
odoo14_addon_stock_available_base_exclude_location-14.0.1.0.2.dist-info/top_level.txt
odoo14_addon_stock_available_base_exclude_location-14.0.1.0.2.dist-info/RECORD
